{
	"ulid": "01K36S5JETT777XMQ5EJX80B5Q",
	"minTime": 1755756003010,
	"maxTime": 1755777600000,
	"stats": {
		"numSamples": 499019,
		"numSeries": 1453,
		"numChunks": 4235
	},
	"compaction": {
		"level": 2,
		"sources": [
			"01K35XPN8JFV4N3VYVK3G0W5XW",
			"01K364J9T97HH06XDES3A9NFMA",
			"01K36BE3RZHYXZFR2AZ11MH1B2"
		],
		"parents": [
			{
				"ulid": "01K35XPN8JFV4N3VYVK3G0W5XW",
				"minTime": 1755756003010,
				"maxTime": 1755763200000
			},
			{
				"ulid": "01K364J9T97HH06XDES3A9NFMA",
				"minTime": 1755763203006,
				"maxTime": 1755770400000
			},
			{
				"ulid": "01K36BE3RZHYXZFR2AZ11MH1B2",
				"minTime": 1755770403006,
				"maxTime": 1755777600000
			}
		]
	},
	"version": 1
}